duckduckgo_async_search/__init__.py
duckduckgo_async_search/api.py
duckduckgo_async_search/client.py
duckduckgo_async_search-1.0.0.dist-info/licenses/LICENSE.md
duckduckgo_async_search-1.0.0.dist-info/METADATA
duckduckgo_async_search-1.0.0.dist-info/WHEEL
duckduckgo_async_search-1.0.0.dist-info/top_level.txt
duckduckgo_async_search-1.0.0.dist-info/RECORD
