Metadata-Version: 2.4
Name: duckduckgo-async-search
Version: 1.0.0
Summary: Async DuckDuckGo search helper with SERP wrapper + Instant Answer API fallback.
Author: S M Abrar Jahin
License-Expression: MIT
Project-URL: Homepage, https://github.com/AbrarJahin/pip-duckduckgo_async_search
Project-URL: Repository, https://github.com/AbrarJahin/pip-duckduckgo_async_search
Project-URL: Issues, https://github.com/AbrarJahin/pip-duckduckgo_async_search/issues
Keywords: duckduckgo,search,async,httpx
Requires-Python: >=3.9
License-File: LICENSE.md
Requires-Dist: httpx>=0.27
Requires-Dist: ddgs>=9.0.0
Dynamic: license-file
